README.md
setup.py
kfk2es/__init__.py
kfk2es.egg-info/PKG-INFO
kfk2es.egg-info/SOURCES.txt
kfk2es.egg-info/dependency_links.txt
kfk2es.egg-info/requires.txt
kfk2es.egg-info/top_level.txt