Metadata-Version: 2.1
Name: kfk2es
Version: 1.1.0
Summary: get data from kafka, after processing send them to elasticsearch
Home-page: https://github.com/thuhak/kfk2es
Author: thuhak
Author-email: thuhak.zhou@nio.com
License: UNKNOWN
Keywords: kafka elasticsearch logstash
Platform: UNKNOWN
